jintonic/__init__.py
jintonic/__main__.py
jintonic/chords.py
jintonic/harmonics.py
jintonic/intervals.py
jintonic/lattice.py
jintonic/primes.py
jintonic/scales.py
jintonic-0.2.6.dist-info/LICENSE
jintonic-0.2.6.dist-info/METADATA
jintonic-0.2.6.dist-info/WHEEL
jintonic-0.2.6.dist-info/entry_points.txt
jintonic-0.2.6.dist-info/top_level.txt
jintonic-0.2.6.dist-info/RECORD
