Metadata-Version: 2.1
Name: jintonic
Version: 0.2.6
Summary: Utilities for computer assisted composition in just intonation
Author: Ismail Negm
Classifier: Programming Language :: Python :: 3
Classifier: License :: OSI Approved :: MIT License
Classifier: Operating System :: OS Independent
Requires-Python: >=3.7
License-File: LICENSE
